strangeworks_jupyterlab_theme/__init__.py
strangeworks_jupyterlab_theme/labextension/package.json
strangeworks_jupyterlab_theme/labextension/static/665.74f38c425ba02a6b59eb.js
strangeworks_jupyterlab_theme/labextension/static/980.37197e91da47ed8b62ab.js
strangeworks_jupyterlab_theme/labextension/static/remoteEntry.32cda03da57891f90843.js
strangeworks_jupyterlab_theme/labextension/static/style.js
strangeworks_jupyterlab_theme/labextension/static/third-party-licenses.json
strangeworks_jupyterlab_theme/labextension/themes/@strangeworks/jupyterlab-theme/index.css
strangeworks_jupyterlab_theme/labextension/themes/@strangeworks/jupyterlab-theme/index.js
strangeworks_jupyterlab_theme-0.1.1.data/data/share/jupyter/labextensions/@strangeworks/jupyterlab-theme/package.json
strangeworks_jupyterlab_theme-0.1.1.data/data/share/jupyter/labextensions/@strangeworks/jupyterlab-theme/static/665.74f38c425ba02a6b59eb.js
strangeworks_jupyterlab_theme-0.1.1.data/data/share/jupyter/labextensions/@strangeworks/jupyterlab-theme/static/980.37197e91da47ed8b62ab.js
strangeworks_jupyterlab_theme-0.1.1.data/data/share/jupyter/labextensions/@strangeworks/jupyterlab-theme/static/remoteEntry.32cda03da57891f90843.js
strangeworks_jupyterlab_theme-0.1.1.data/data/share/jupyter/labextensions/@strangeworks/jupyterlab-theme/static/style.js
strangeworks_jupyterlab_theme-0.1.1.data/data/share/jupyter/labextensions/@strangeworks/jupyterlab-theme/static/third-party-licenses.json
strangeworks_jupyterlab_theme-0.1.1.data/data/share/jupyter/labextensions/@strangeworks/jupyterlab-theme/themes/@strangeworks/jupyterlab-theme/index.css
strangeworks_jupyterlab_theme-0.1.1.data/data/share/jupyter/labextensions/@strangeworks/jupyterlab-theme/themes/@strangeworks/jupyterlab-theme/index.js
strangeworks_jupyterlab_theme-0.1.1.data/data/share/jupyter/labextensions/@strangeworks/jupyterlab-theme/install.json
strangeworks_jupyterlab_theme-0.1.1.dist-info/METADATA
strangeworks_jupyterlab_theme-0.1.1.dist-info/WHEEL
strangeworks_jupyterlab_theme-0.1.1.dist-info/licenses/LICENSE
strangeworks_jupyterlab_theme-0.1.1.dist-info/RECORD
