Metadata-Version: 2.4
Name: strangeworks_jupyterlab_theme
Version: 0.1.1
Summary: Strangeworks dark theme for JupyterLab
Author-email: Strangeworks <support@strangeworks.com>
License: BSD 3-Clause License
License-File: LICENSE
Keywords: jupyter,jupyterlab,strangeworks,theme
Classifier: Framework :: Jupyter
Classifier: Framework :: Jupyter :: JupyterLab
Classifier: Framework :: Jupyter :: JupyterLab :: 4
Classifier: Framework :: Jupyter :: JupyterLab :: Extensions
Classifier: Framework :: Jupyter :: JupyterLab :: Extensions :: Prebuilt
Classifier: License :: OSI Approved :: BSD License
Classifier: Programming Language :: Python
Classifier: Programming Language :: Python :: 3
Classifier: Programming Language :: Python :: 3.8
Classifier: Programming Language :: Python :: 3.9
Classifier: Programming Language :: Python :: 3.10
Classifier: Programming Language :: Python :: 3.11
Requires-Python: >=3.8
